local_mcp_server/__init__.py
local_mcp_server/cli.py
local_mcp_server/client.py
local_mcp_server/config.py
local_mcp_server/helper.py
local_mcp_server-0.2.2.dist-info/METADATA
local_mcp_server-0.2.2.dist-info/WHEEL
local_mcp_server-0.2.2.dist-info/entry_points.txt
local_mcp_server-0.2.2.dist-info/RECORD
