Metadata-Version: 2.4
Name: local-mcp-server
Version: 0.2.2
Summary: Local MCP Server
Requires-Python: >=3.13
Requires-Dist: httpx>=0.28.1
Requires-Dist: mcp[cli]>=1.6.0
Requires-Dist: pydantic>=2.11.1
Requires-Dist: requests>=2.32.3
